amazigh_date/__init__.py
amazigh_date/_core.py
amazigh_date/cli.py
amazigh_date-2026.2.dist-info/METADATA
amazigh_date-2026.2.dist-info/WHEEL
amazigh_date-2026.2.dist-info/entry_points.txt
amazigh_date-2026.2.dist-info/RECORD
