Metadata-Version: 2.4
Name: amazigh-date
Version: 2026.2
Summary: Amazigh (Berber) calendar library and CLI
Author-email: Athmane MOKRAOUI <butterflyoffire+pypi@protonmail.com>
License-Expression: CC0-1.0
Keywords: amazigh,berber,calendar,date,yennayer
Classifier: Intended Audience :: Developers
Classifier: Programming Language :: Python :: 3
Classifier: Programming Language :: Python :: 3 :: Only
Classifier: Topic :: Software Development :: Libraries
Classifier: Topic :: Software Development :: Libraries :: Python Modules
Classifier: Topic :: Utilities
Requires-Python: >=3.8
